mpesa/__init__.py
mpesa/gateway.py
mpesa/urls.py
mpesa_api_sdk-0.1.dist-info/METADATA
mpesa_api_sdk-0.1.dist-info/RECORD
mpesa_api_sdk-0.1.dist-info/WHEEL
mpesa_api_sdk-0.1.dist-info/dependency_links.txt
mpesa_api_sdk-0.1.dist-info/top_level.txt
